genx/__init__.py
genx/__main__.py
genx/api.py
genx/bumps_optimizer.py
genx/data.py
genx/diffev.py
genx/exceptions.py
genx/fom_funcs.py
genx/levenberg_marquardt.py
genx/model.py
genx/model_actions.py
genx/model_control.py
genx/parameters.py
genx/run.py
genx/server.py
genx/solver_basis.py
genx/version.py
genx/core/Simplex.py
genx/core/__init__.py
genx/core/colors.py
genx/core/config.py
genx/core/console.py
genx/core/custom_logging.py
genx/core/decorators.py
genx/core/h5_support.py
genx/examples/D17_SiO.out
genx/examples/D17_TOF_SiO.hgx
genx/examples/Neutron_SiO_ref.dat
genx/examples/Peakfit_Gauss.hgx
genx/examples/Peakfit_Gauss_coupled_pars.hgx
genx/examples/Peakfit_Voigt.hgx
genx/examples/SXRD.hgx
genx/examples/SXRD2.hgx
genx/examples/SuperAdam_SiO.hgx
genx/examples/SuperAdam_SiO_advanced_fp_res.hgx
genx/examples/SuperAdam_SiO_full_res_calc.hgx
genx/examples/SuperAdam_SiO_systematic_errors.hgx
genx/examples/X-ray_Reflectivity.hgx
genx/examples/X-ray_Reflectivity_kalpha.hgx
genx/examples/bumps_integration.ipynb
genx/examples/load_fit_save.ipynb
genx/examples/publication_graphics.ipynb
genx/examples/reflectivity_interface.ipynb
genx/examples/widget_test.ipynb
genx/examples/xray-tutorial.dat
genx/gui/__init__.py
genx/gui/batch_dialog.py
genx/gui/bumps_interface.py
genx/gui/bumps_notebook.py
genx/gui/controls.py
genx/gui/custom_choice_dialog.py
genx/gui/custom_events.py
genx/gui/custom_ids.py
genx/gui/datalist.py
genx/gui/exception_handling.py
genx/gui/help.py
genx/gui/history_dialog.py
genx/gui/images.py
genx/gui/log_dialog.py
genx/gui/main_window.py
genx/gui/message_dialogs.py
genx/gui/metadata_dialog.py
genx/gui/online_update.py
genx/gui/output_dialog.py
genx/gui/parametergrid.py
genx/gui/plot_dialog.py
genx/gui/plotpanel.py
genx/gui/plotpanel_wx.py
genx/gui/pubgraph_dialog.py
genx/gui/settings_dialog.py
genx/gui/solvergui.py
genx/models/__init__.py
genx/models/interdiff.py
genx/models/mag_refl.py
genx/models/soft_nx.py
genx/models/spec_adaptive.py
genx3-3.7.14.dist-info/licenses/LICENSE.txt
genx3-3.7.14.dist-info/METADATA
genx3-3.7.14.dist-info/WHEEL
genx3-3.7.14.dist-info/entry_points.txt
genx3-3.7.14.dist-info/top_level.txt
genx3-3.7.14.dist-info/RECORD
