Metadata-Version: 2.4
Name: genx3
Version: 3.7.14
Summary: X-ray and Neutron reflectivity fitting software.
Home-page: https://github.com/aglavic/genx
Author: Artur Glavic, Matts Bjorck
Author-email: artur.glavic@psi.ch
License: GPL v3
Classifier: Programming Language :: Python :: 3
Classifier: License :: OSI Approved :: GNU General Public License v3 (GPLv3)
Classifier: Operating System :: OS Independent
Classifier: Topic :: Scientific/Engineering :: Physics
Classifier: Development Status :: 6 - Mature
Requires-Python: >=3.6
License-File: LICENSE.txt
Requires-Dist: numpy
Requires-Dist: matplotlib
Requires-Dist: scipy
Requires-Dist: platformdirs
Requires-Dist: h5py
Requires-Dist: orsopy>=1.2.0
Requires-Dist: wxpython
Requires-Dist: requests
Requires-Dist: docutils
Requires-Dist: pint
Requires-Dist: svgwrite
Dynamic: license-file
